papaya/__init__.py
papaya/conf.py
papaya/util.py
papaya/version.py
papaya/backends/__init__.py
papaya/backends/ldapauth.py
papaya/backends/openidauth.py
papaya/consumer/__init__.py
papaya/consumer/forms.py
papaya/consumer/urls.py
papaya/consumer/views.py
papaya/consumer/templates/consumer/index.html
papaya/consumer/templates/consumer/request_form.html
papaya/server/__init__.py
papaya/server/urls.py
papaya/server/views.py
papaya/server/templates/server/base.html
papaya/server/templates/server/endpoint.html
papaya/server/templates/server/idPage.html
papaya/server/templates/server/index.html
papaya/server/templates/server/trust.html
papaya/server/templatetags/__init__.py
papaya/server/templatetags/server_tags.py
papaya-0.3.0.dist-info/DESCRIPTION.rst
papaya-0.3.0.dist-info/METADATA
papaya-0.3.0.dist-info/RECORD
papaya-0.3.0.dist-info/WHEEL
papaya-0.3.0.dist-info/metadata.json
papaya-0.3.0.dist-info/top_level.txt
