Metadata-Version: 2.0
Name: papaya
Version: 0.3.0
Summary: A LDAP-based django authentication provider, with openid.
Home-page: https://github.com/Polyconseil/papaya
Author: Polyconseil Sysadmin Team
Author-email: sysadmin+papaya@polyconseil.fr
License: GPL
Keywords: papaya,ldap,authentication,django,openid
Platform: UNKNOWN
Classifier: Development Status :: 4 - Beta
Classifier: Environment :: Console
Classifier: Environment :: Web Environment
Classifier: Framework :: Django :: 1.11
Classifier: Intended Audience :: System Administrators
Classifier: License :: OSI Approved :: GNU General Public License v3 (GPLv3)
Classifier: Programming Language :: Python :: 2.7
Classifier: Programming Language :: Python :: 3.4
Classifier: Programming Language :: Python :: 3.5
Classifier: Programming Language :: Python :: 3.6
Classifier: Topic :: System :: Systems Administration :: Authentication/Directory :: LDAP
Requires-Dist: Django (>=1.11)
Requires-Dist: django-appconf
Requires-Dist: pyldap
Requires-Dist: python-openid
